LICENSE
README.md
setup.cfg
setup.py
src/Qiskit_PTesting/ExtraFunctions.py
src/Qiskit_PTesting/Qiskit_PTesting.py
src/Qiskit_PTesting/StatisticalAnalysisEngine.py
src/Qiskit_PTesting/TestCaseGeneration.py
src/Qiskit_PTesting/TestExecutionEngine.py
src/Qiskit_PTesting/TestProperties.py
src/Qiskit_PTesting/__init__.py
src/qiskit_ptesting.egg-info/PKG-INFO
src/qiskit_ptesting.egg-info/SOURCES.txt
src/qiskit_ptesting.egg-info/dependency_links.txt
src/qiskit_ptesting.egg-info/requires.txt
src/qiskit_ptesting.egg-info/top_level.txt