Metadata-Version: 2.1
Name: qiskit-ptesting
Version: 0.1.5
Summary: Property-based testing framework for qiskit algorithms.
Home-page: https://gitlab.com/twistercool/Qiskit-PTesting
Author: Pierre Brassart
Author-email: pierrebrassart80@hotmail.fr
License: Apache 2.0
Keywords: qiskit property testing
Platform: UNKNOWN
Classifier: Development Status :: 3 - Alpha
Requires-Python: >=3.6
License-File: LICENSE
